architectonics/__init__.py
architectonics/common/__init__.py
architectonics/common/consts/__init__.py
architectonics/common/enums/__init__.py
architectonics/common/enums/step_type.py
architectonics/common/utils/utils.py
architectonics/contracts/__init__.py
architectonics/contracts/step_model/__init__.py
architectonics/contracts/step_model/step_model_contract.py
architectonics/core/__init__.py
architectonics/core/config/__init__.py
architectonics/core/config/application_settings.py
architectonics/core/factory/__init__.py
architectonics/core/factory/factory.py
architectonics/core/models/__init__.py
architectonics/core/models/base_model.py
architectonics/core/models/deleted_models.py
architectonics/core/result/error_message.py
architectonics/core/result/service_result.py
architectonics/core/schemas/base_schemas.py
architectonics/core/services/base_schemas.py
architectonics/core/services/base_service.py
architectonics/core/services/user_auth_service.py
architectonics/core/validation/base_model_validation_errors.py
architectonics/infrastructure/__init__.py
architectonics/infrastructure/config/__init__.py
architectonics/infrastructure/config/database.py
architectonics/infrastructure/config/database_settings.py
architectonics/infrastructure/entities/base_entity.py
architectonics/infrastructure/repositories/__init__.py
architectonics/infrastructure/repositories/base_exceptions.py
architectonics/infrastructure/repositories/base_repository.py
architectonics/rabbit_mq/__init__.py
architectonics/rabbit_mq/config/__init__.py
architectonics/rabbit_mq/config/rabbit_mq_settings.py
architectonics/rabbit_mq/consumer/__init__.py
architectonics/rabbit_mq/consumer/base_consumer.py
architectonics-0.0.41.dist-info/WHEEL
architectonics-0.0.41.dist-info/METADATA
architectonics-0.0.41.dist-info/RECORD
