Metadata-Version: 2.1
Name: architectonics
Version: 0.0.41
Summary: 
Author: Your Name
Author-email: you@example.com
Requires-Python: >=3.14,<4.0
Classifier: Programming Language :: Python :: 3
Requires-Dist: SQLAlchemy (==2.0.46)
Requires-Dist: aio-pika (==9.5.8)
Requires-Dist: alembic (==1.18.1)
Requires-Dist: asyncpg (==0.31.0)
Requires-Dist: dotenv (==0.9.9)
Requires-Dist: fastapi (==0.128.0)
Requires-Dist: pydantic (==2.12.5)
Requires-Dist: uvicorn (==0.40.0)
